HC_SR04.py
tools/__init__.py
tools/serial.py
tools/test.py
tools/tester.py
HC_SR04-0.3.1.dist-info/LICENSE
HC_SR04-0.3.1.dist-info/METADATA
HC_SR04-0.3.1.dist-info/WHEEL
HC_SR04-0.3.1.dist-info/top_level.txt
HC_SR04-0.3.1.dist-info/RECORD
