Metadata-Version: 2.1
Name: HC_SR04
Version: 0.3.1
Summary: HC-SR04 Python module via Serial protocol
Home-page: https://github.com/KKimj/HC-SR04_Python-library
Author: KKimj
Author-email: kkimj@hanyang.ac.kr
License: GPL-3.0 License
Platform: UNKNOWN
Classifier: Programming Language :: Python :: 3
Classifier: License :: OSI Approved :: GNU General Public License v3 (GPLv3)
Classifier: Operating System :: OS Independent
Classifier: Topic :: Terminals :: Serial
Classifier: Natural Language :: Korean
Requires-Python: >=3
